<?xml version="1.0" encoding="UTF-8"?>
<!DOCTYPE mapper
        PUBLIC "-//mybatis.org//DTD Mapper 3.0//EN"
        "http://mybatis.org/dtd/mybatis-3-mapper.dtd">

<mapper namespace="kr.com.brorder.store.Store">

    <!-- 1. 판매처 전체 목록 조회 -->
    <select id="selectStoreList" resultType="kr.com.brorder.store.Store">
        SELECT
            store_id     AS storeId,
            name,
            category,
            address,
            phone,
            rating,
            created_data AS createdData,
            status
        FROM
            store
        ORDER BY
            store_id DESC
    </select>

    <!-- 2. 특정 판매처 단건 상세 조회 -->
    <select id="selectStoreById" parameterType="java.lang.Integer" resultType="kr.com.brorder.store.Store">
        SELECT
            store_id     AS storeId,
            name,
            category,
            address,
            phone,
            rating,
            created_data AS createdData,
            status
        FROM
            store
        WHERE
            store_id = #{store_id}
    </select>

    <!-- 3. 가게 등록 -->
    <insert id="insertStore" parameterType="kr.com.brorder.store.Store">
        INSERT INTO store (name, category, address, phone, rating, created_data, status)
        VALUES (#{name}, #{category}, #{address}, #{phone}, 5, NOW(), 'OPEN')
    </insert>

    <!-- 4. 가게 수정 -->
    <update id="updateStore" parameterType="kr.com.brorder.store.Store">
        UPDATE store
        SET name = #{name},
            category = #{category},
            address = #{address},
            phone = #{phone},
            status = #{status}
        WHERE store_id = #{storeId}
    </update>

    <!-- 5. 가게 삭제 -->
    <delete id="deleteStore" parameterType="java.lang.Integer">
        DELETE FROM store WHERE store_id = #{storeId}
    </delete>

</mapper>